cvtrafficregenerator/CVTrafficRegenerator.py
cvtrafficregenerator/__init__.py
cvtrafficregenerator-1.0.2.dist-info/entry_points.txt
cvtrafficregenerator-1.0.2.dist-info/LICENSE.txt
cvtrafficregenerator-1.0.2.dist-info/WHEEL
cvtrafficregenerator-1.0.2.dist-info/METADATA
cvtrafficregenerator-1.0.2.dist-info/RECORD
