Metadata-Version: 2.1
Name: cvtrafficregenerator
Version: 1.0.2
Summary: To regenerate events traffic in CloudVector API Shark when there is change in API spec
License: MIT
Keywords: cvtrafficregenerator,cloudvector,apishark
Author: Bala Kumaran
Author-email: balak@cloudvector.com
Requires-Python: >=3.5,<4.0
Classifier: Environment :: Console
Classifier: License :: OSI Approved :: MIT License
Classifier: Operating System :: OS Independent
Classifier: Programming Language :: Python :: 3
Classifier: Programming Language :: Python :: 3.5
Classifier: Programming Language :: Python :: 3.6
Classifier: Programming Language :: Python :: 3.7
Classifier: Programming Language :: Python :: 3.8
Classifier: Topic :: Software Development :: Documentation
Classifier: Topic :: Software Development :: Libraries :: Python Modules
Classifier: Topic :: Software Development :: Quality Assurance
Requires-Dist: cvapianalyser (>=1.2,<2.0)
Requires-Dist: openapispecdiff
